{"name":"Title of your scenario","id":"make-a-purchase;title-of-your-scenario","testSteps":[{"number":1,"description":"Given I want to write a step with precondition","duration":6,"startTime":"2021-08-05T10:49:21.236854800-05:00[America/Bogota]","result":"PENDING","precondition":false,"level":0},{"number":2,"description":"And some other precondition","duration":9,"startTime":"2021-08-05T10:49:21.244856700-05:00[America/Bogota]","result":"IGNORED","precondition":false,"level":0},{"number":3,"description":"When I complete action","duration":7,"startTime":"2021-08-05T10:49:21.255858-05:00[America/Bogota]","result":"IGNORED","precondition":false,"level":0},{"number":4,"description":"And some other action","duration":6,"startTime":"2021-08-05T10:49:21.264857200-05:00[America/Bogota]","result":"IGNORED","precondition":false,"level":0},{"number":5,"description":"And yet another action","duration":5,"startTime":"2021-08-05T10:49:21.272859100-05:00[America/Bogota]","result":"IGNORED","precondition":false,"level":0},{"number":6,"description":"Then I validate the outcomes","duration":6,"startTime":"2021-08-05T10:49:21.280859400-05:00[America/Bogota]","result":"IGNORED","precondition":false,"level":0},{"number":7,"description":"And check more outcomes","duration":6,"startTime":"2021-08-05T10:49:21.288860400-05:00[America/Bogota]","result":"IGNORED","precondition":false,"level":0}],"userStory":{"id":"make-a-purchase","storyName":"Make a purchase","path":"file:///C:/Users/juan.blanco/Documents/semilleroTesting/SemilleroRefuerzo/SauceDemo/lib/src/test/java/com/sophossolutions/features/make_a_purchase.feature","narrative":"  I want to make a purchase in this store","type":"feature"},"featureTag":{"name":"Features/Make a purchase","type":"feature","displayName":"Features/Make a purchase"},"title":"Title of your scenario","startTime":"2021-08-05T10:49:21.224856-05:00[America/Bogota]","duration":73,"projectKey":"","annotatedResult":"PENDING","isManualTestingUpToDate":false,"manual":false,"testSource":"Cucumber","result":"PENDING"}